{"name":"Single-select-dropdown","tagline":"Select","body":"Single-Select-DropDown\r\n======================\r\n\r\nDemo\r\n\r\n            <div class=\"singleDD fl\" id=\"sal_dd\">\r\n                <div class=\"dWrap\">\r\n                    <input class=\"sdTxt\" type=\"text\" name=\"abc\" placeholder=\"Experience\" readonly/>\r\n                    <span class=\"smArw\"></span>\r\n                </div>\r\n            </div>\r\n","google":"UA-55646101-1","note":"Don't delete this file! It's used internally to help with page regeneration."}